{
  "faq": [
    {
      "question": "行き方・道順・アクセスを教えてください",
      "answer": "JR高槻駅から徒歩2分、阪急高槻市駅から徒歩4分です。高槻センター街（商店街）の中、DAISO 高槻センター街店の目の前のビル2階にあります。住所は大阪府高槻市紺屋町７－１９ ＩＩＤＡビル２Ｆです。"
    },
    {
      "question": "どこにありますか？",
      "answer": "大阪府高槻市紺屋町７－１９ ＩＩＤＡビル２Ｆです。JR高槻駅から徒歩2分、阪急高槻市駅から徒歩4分で、高槻センター街のDAISO前のビル2階です。"
    },
    {
      "question": "営業時間は何時から何時までですか？",
      "answer": "営業時間は9:00～21:00です。定休日は1月1～4日です。"
    },
    {
      "question": "支払い方法は何がありますか？",
      "answer": "Visa、Mastercard、JCB、American Express、Diners Club、PayPay、メルPay、QUICPay、d払い、楽天Payが利用できます。"
    },
    {
      "question": "ロング料金はかかりますか？",
      "answer": "掲載上、ロング料金なしです。"
    },
    {
      "question": "価格は税込ですか？",
      "answer": "掲載価格は税込表示です。"
    },
    {
      "question": "白髪ぼかしメニューはありますか？",
      "answer": "あります。代表的な掲載クーポンでは、白髪ぼかしカラー+カット+oggiotto1stepTr が9,500円です。適用条件は予約時に対象クーポンをご確認ください。"
    },
    {
      "question": "縮毛矯正や酸性ストレートはありますか？",
      "answer": "あります。髪質改善縮毛矯正、美髪縮毛矯正、絹髪髪質改善酸性ストレートの掲載があります。料金や条件はメニューごとに異なります。"
    },
    {
      "question": "メンズメニューはありますか？",
      "answer": "あります。メンズカット、眉カット付き、メンズパーマの掲載があります。男性限定条件があるため、予約時に対象クーポンをご確認ください。"
    },
    {
      "question": "誰が縮毛矯正が得意ですか？",
      "answer": "掲載上では、近藤なつみが『縮毛矯正得意です』と案内されています。"
    },
    {
      "question": "ヘアセットはできますか？",
      "answer": "掲載上では、山下みさきがヘアセット対応で、ヘアセット指名予約は連絡が必要と案内されています。"
    },
    {
      "question": "当日予約できますか？",
      "answer": "当日の予約受付自体は掲載上ありますが、最新の空き状況は予約ページでご確認ください。"
    },
    {
      "question": "わからない内容を聞かれたら？",
      "answer": "掲載情報では確認できません。店舗へ直接ご確認ください。"
    },
    {
      "question": "予約の変更はできますか？",
      "answer": "ホットペッパービューティーの予約ページまたは店舗へ直接お電話でお申し付けください。変更希望の新しい日時が決まりましたら、できるだけお早めにご連絡ください。ご希望に添えない場合もあります。"
    },
    {
      "question": "キャンセルはどうすればいいですか？",
      "answer": "ホットペッパービューティーの予約ページからキャンセル手続きいただくか、店舗へ直接お電話でお申し付けください。当日キャンセルはできるだけお控えいただき、前日までのご連絡にご協力をお願いします。"
    },
    {
      "question": "遅刻しそうな場合はどうすればいいですか？",
      "answer": "わかり次第、店舗へ直接お電話でご連絡ください。ご来店時間によっては、施術内容や日時の変更をお願いする場合があります。"
    }
  ]
}
